mathsolver/__init__.py
mathsolver/extractor.py
mathsolver/math_thesaurus.py
mathsolver/mathsolver.py
mathsolver-0.1.0.dist-info/LICENSE
mathsolver-0.1.0.dist-info/METADATA
mathsolver-0.1.0.dist-info/WHEEL
mathsolver-0.1.0.dist-info/top_level.txt
mathsolver-0.1.0.dist-info/RECORD
