Metadata-Version: 2.1
Name: mathsolver
Version: 0.1.0
Summary: Decode natural language to solve mathemathical calculations
Home-page: https://github.com/maverickjoy/mathsolver
Author: Vikram Singh
Author-email: mailvikram@email.com
License: MIT
Platform: UNKNOWN
Classifier: Development Status :: 4 - Beta
Classifier: Intended Audience :: Developers
Classifier: License :: OSI Approved :: MIT License
Classifier: Operating System :: OS Independent
Classifier: Topic :: Software Development :: Libraries :: Python Modules
Classifier: Topic :: Scientific/Engineering :: Mathematics
Classifier: Topic :: Text Processing :: General
Classifier: Topic :: Text Processing :: Linguistic
Classifier: Programming Language :: Python
